tests/__init__.py
tests/test_wkw.py
wkw/__init__.py
wkw/wkw.py
wkw/lib/libwkw.dylib
wkw/lib/wkw.h
wkw-1.1.24.dist-info/METADATA
wkw-1.1.24.dist-info/WHEEL
wkw-1.1.24.dist-info/top_level.txt
wkw-1.1.24.dist-info/RECORD
