Metadata-Version: 2.1
Name: wkw
Version: 1.1.24
Home-page: https://github.com/scalableminds/webknossos-wrap
Author: Alessandro Motta
Author-email: alessandro.motta@brain.mpg.de
License: MIT
Requires-Dist: cffi
Requires-Dist: numpy>=1.15
